nsa_fusion-1.4.2.dist-info/licenses/LICENSE
nsarchive/__init__.py
nsarchive/database.py
nsarchive/drive.py
nsarchive/mandate.py
nsarchive/utils.py
nsarchive/functions/commons.py
nsarchive/interfaces/_economy.py
nsarchive/interfaces/_entities.py
nsarchive/interfaces/_justice.py
nsarchive/interfaces/_state.py
nsarchive/models/base.py
nsarchive/models/economy.py
nsarchive/models/entities.py
nsarchive/models/justice.py
nsarchive/models/scale.py
nsarchive/models/state.py
nsarchive/tools/__init__.py
nsa_fusion-1.4.2.dist-info/METADATA
nsa_fusion-1.4.2.dist-info/WHEEL
nsa_fusion-1.4.2.dist-info/top_level.txt
nsa_fusion-1.4.2.dist-info/RECORD
