Metadata-Version: 2.4
Name: nsa-fusion
Version: 1.4.2
Summary: API-wrapper pour récupérer des données liées à Nation
Author-email: happex <110610727+okayhappex@users.noreply.github.com>
License-Expression: GPL-3.0
Requires-Python: >=3.10
License-File: LICENSE
Requires-Dist: pillow>=10.4
Dynamic: license-file
